{
  "feature": "integrations",
  "facets": [
    {
      "id": "features/integrations/dx:developer-experience",
      "source": {
        "file": "facets/dx.md",
        "section": "developer-experience"
      },
      "type": "dx",
      "title": "Developer Experience"
    },
    {
      "id": "features/integrations/dx:simplicity",
      "source": {
        "file": "facets/dx.md",
        "section": "simplicity"
      },
      "type": "dx",
      "title": "Integration Simplicity"
    },
    {
      "id": "features/integrations/dx:simplicity/minimal-config",
      "source": {
        "file": "facets/dx.md",
        "section": "simplicity",
        "line": 9
      },
      "type": "dx",
      "parentId": "features/integrations/dx:simplicity",
      "isSubFacet": true
    },
    {
      "id": "features/integrations/dx:simplicity/clear-imports",
      "source": {
        "file": "facets/dx.md",
        "section": "simplicity",
        "line": 10
      },
      "type": "dx",
      "parentId": "features/integrations/dx:simplicity",
      "isSubFacet": true
    },
    {
      "id": "features/integrations/dx:simplicity/playwright-compat",
      "source": {
        "file": "facets/dx.md",
        "section": "simplicity",
        "line": 11
      },
      "type": "dx",
      "parentId": "features/integrations/dx:simplicity",
      "isSubFacet": true
    },
    {
      "id": "features/integrations/dx:simplicity/no-modifications",
      "source": {
        "file": "facets/dx.md",
        "section": "simplicity",
        "line": 12
      },
      "type": "dx",
      "parentId": "features/integrations/dx:simplicity",
      "isSubFacet": true
    },
    {
      "id": "features/integrations/dx:annotation-syntax",
      "source": {
        "file": "facets/dx.md",
        "section": "annotation-syntax"
      },
      "type": "dx",
      "title": "Annotation Syntax"
    },
    {
      "id": "features/integrations/dx:annotation-syntax/multi-id-annotation",
      "source": {
        "file": "facets/dx.md",
        "section": "annotation-syntax",
        "line": 20
      },
      "type": "dx",
      "parentId": "features/integrations/dx:annotation-syntax",
      "isSubFacet": true
    },
    {
      "id": "features/integrations/dx:annotation-syntax/natural-syntax",
      "source": {
        "file": "facets/dx.md",
        "section": "annotation-syntax",
        "line": 21
      },
      "type": "dx",
      "parentId": "features/integrations/dx:annotation-syntax",
      "isSubFacet": true
    },
    {
      "id": "features/integrations/dx:annotation-syntax/separation",
      "source": {
        "file": "facets/dx.md",
        "section": "annotation-syntax",
        "line": 22
      },
      "type": "dx",
      "parentId": "features/integrations/dx:annotation-syntax",
      "isSubFacet": true
    },
    {
      "id": "features/integrations/dx:annotation-syntax/annotation-types",
      "source": {
        "file": "facets/dx.md",
        "section": "annotation-syntax",
        "line": 23
      },
      "type": "dx",
      "parentId": "features/integrations/dx:annotation-syntax",
      "isSubFacet": true
    },
    {
      "id": "features/integrations/product:integrations",
      "source": {
        "file": "facets/product.md",
        "section": "integrations"
      },
      "type": "product",
      "title": "Integrations"
    },
    {
      "id": "features/integrations/product:facet-function",
      "source": {
        "file": "facets/product.md",
        "section": "facet-function"
      },
      "type": "product",
      "title": "Type-Safe Facet Function"
    },
    {
      "id": "features/integrations/product:facet-function/variadic-args",
      "source": {
        "file": "facets/product.md",
        "section": "facet-function",
        "line": 9
      },
      "type": "product",
      "parentId": "features/integrations/product:facet-function",
      "isSubFacet": true
    },
    {
      "id": "features/integrations/product:facet-function/typescript-autocomplete",
      "source": {
        "file": "facets/product.md",
        "section": "facet-function",
        "line": 10
      },
      "type": "product",
      "parentId": "features/integrations/product:facet-function",
      "isSubFacet": true
    },
    {
      "id": "features/integrations/product:facet-function/framework-agnostic",
      "source": {
        "file": "facets/product.md",
        "section": "facet-function",
        "line": 11
      },
      "type": "product",
      "parentId": "features/integrations/product:facet-function",
      "isSubFacet": true
    },
    {
      "id": "features/integrations/product:facet-function/constant-refs",
      "source": {
        "file": "facets/product.md",
        "section": "facet-function",
        "line": 12
      },
      "type": "product",
      "parentId": "features/integrations/product:facet-function",
      "isSubFacet": true
    },
    {
      "id": "features/integrations/product:facet-function/multiple-ids",
      "source": {
        "file": "facets/product.md",
        "section": "facet-function",
        "line": 13
      },
      "type": "product",
      "parentId": "features/integrations/product:facet-function",
      "isSubFacet": true
    },
    {
      "id": "features/integrations/product:facet-function/metadata-return",
      "source": {
        "file": "facets/product.md",
        "section": "facet-function",
        "line": 14
      },
      "type": "product",
      "parentId": "features/integrations/product:facet-function",
      "isSubFacet": true
    },
    {
      "id": "features/integrations/product:facet-function/compile-time-check",
      "source": {
        "file": "facets/product.md",
        "section": "facet-function",
        "line": 15
      },
      "type": "product",
      "parentId": "features/integrations/product:facet-function",
      "isSubFacet": true
    },
    {
      "id": "features/integrations/product:playwright-helper",
      "source": {
        "file": "facets/product.md",
        "section": "playwright-helper"
      },
      "type": "product",
      "title": "Playwright Annotation Helper"
    },
    {
      "id": "features/integrations/product:playwright-helper/pw-facet-function",
      "source": {
        "file": "facets/product.md",
        "section": "playwright-helper",
        "line": 34
      },
      "type": "product",
      "parentId": "features/integrations/product:playwright-helper",
      "isSubFacet": true
    },
    {
      "id": "features/integrations/product:playwright-helper/pw-annotation-object",
      "source": {
        "file": "facets/product.md",
        "section": "playwright-helper",
        "line": 35
      },
      "type": "product",
      "parentId": "features/integrations/product:playwright-helper",
      "isSubFacet": true
    },
    {
      "id": "features/integrations/product:playwright-helper/pw-multiple-ids",
      "source": {
        "file": "facets/product.md",
        "section": "playwright-helper",
        "line": 36
      },
      "type": "product",
      "parentId": "features/integrations/product:playwright-helper",
      "isSubFacet": true
    },
    {
      "id": "features/integrations/product:playwright-helper/pw-test-syntax",
      "source": {
        "file": "facets/product.md",
        "section": "playwright-helper",
        "line": 37
      },
      "type": "product",
      "parentId": "features/integrations/product:playwright-helper",
      "isSubFacet": true
    },
    {
      "id": "features/integrations/product:playwright-reporter",
      "source": {
        "file": "facets/product.md",
        "section": "playwright-reporter"
      },
      "type": "product",
      "title": "Playwright Reporter"
    },
    {
      "id": "features/integrations/product:playwright-reporter/pw-reporter-interface",
      "source": {
        "file": "facets/product.md",
        "section": "playwright-reporter",
        "line": 45
      },
      "type": "product",
      "parentId": "features/integrations/product:playwright-reporter",
      "isSubFacet": true
    },
    {
      "id": "features/integrations/product:playwright-reporter/pw-extract-annotations",
      "source": {
        "file": "facets/product.md",
        "section": "playwright-reporter",
        "line": 46
      },
      "type": "product",
      "parentId": "features/integrations/product:playwright-reporter",
      "isSubFacet": true
    },
    {
      "id": "features/integrations/product:playwright-reporter/pw-passed-only",
      "source": {
        "file": "facets/product.md",
        "section": "playwright-reporter",
        "line": 47
      },
      "type": "product",
      "parentId": "features/integrations/product:playwright-reporter",
      "isSubFacet": true
    },
    {
      "id": "features/integrations/product:playwright-reporter/pw-merge-data",
      "source": {
        "file": "facets/product.md",
        "section": "playwright-reporter",
        "line": 48
      },
      "type": "product",
      "parentId": "features/integrations/product:playwright-reporter",
      "isSubFacet": true
    },
    {
      "id": "features/integrations/product:playwright-reporter/pw-report-formats",
      "source": {
        "file": "facets/product.md",
        "section": "playwright-reporter",
        "line": 49
      },
      "type": "product",
      "parentId": "features/integrations/product:playwright-reporter",
      "isSubFacet": true
    },
    {
      "id": "features/integrations/product:playwright-reporter/pw-console-summary",
      "source": {
        "file": "facets/product.md",
        "section": "playwright-reporter",
        "line": 50
      },
      "type": "product",
      "parentId": "features/integrations/product:playwright-reporter",
      "isSubFacet": true
    },
    {
      "id": "features/integrations/product:playwright-reporter/pw-config-options",
      "source": {
        "file": "facets/product.md",
        "section": "playwright-reporter",
        "line": 51
      },
      "type": "product",
      "parentId": "features/integrations/product:playwright-reporter",
      "isSubFacet": true
    },
    {
      "id": "features/integrations/product:playwright-reporter/pw-other-reporters",
      "source": {
        "file": "facets/product.md",
        "section": "playwright-reporter",
        "line": 52
      },
      "type": "product",
      "parentId": "features/integrations/product:playwright-reporter",
      "isSubFacet": true
    }
  ]
}